neuralpy/__init__.py
neuralpy/callbacks/__init__.py
neuralpy/callbacks/train_logger.py
neuralpy/layers/__init__.py
neuralpy/layers/activation_functions/__init__.py
neuralpy/layers/activation_functions/gelu.py
neuralpy/layers/activation_functions/leaky_relu.py
neuralpy/layers/activation_functions/relu.py
neuralpy/layers/activation_functions/selu.py
neuralpy/layers/activation_functions/sigmoid.py
neuralpy/layers/activation_functions/softmax.py
neuralpy/layers/activation_functions/tanh.py
neuralpy/layers/convolutional/__init__.py
neuralpy/layers/convolutional/conv1d.py
neuralpy/layers/convolutional/conv2d.py
neuralpy/layers/convolutional/conv3d.py
neuralpy/layers/linear/__init__.py
neuralpy/layers/linear/bilinear.py
neuralpy/layers/linear/dense.py
neuralpy/layers/normalization/__init__.py
neuralpy/layers/normalization/batchnorm1d.py
neuralpy/layers/normalization/batchnorm2d.py
neuralpy/layers/normalization/batchnorm3d.py
neuralpy/layers/other/__init__.py
neuralpy/layers/other/flatten.py
neuralpy/layers/pooling/__init__.py
neuralpy/layers/pooling/avg_pool1d.py
neuralpy/layers/pooling/avg_pool2d.py
neuralpy/layers/pooling/avg_pool3d.py
neuralpy/layers/pooling/maxpool1d.py
neuralpy/layers/pooling/maxpool2d.py
neuralpy/layers/pooling/maxpool3d.py
neuralpy/layers/recurrent/__init__.py
neuralpy/layers/recurrent/gru.py
neuralpy/layers/recurrent/gru_cell.py
neuralpy/layers/recurrent/lstm.py
neuralpy/layers/recurrent/lstm_cell.py
neuralpy/layers/recurrent/rnn.py
neuralpy/layers/recurrent/rnn_cell.py
neuralpy/layers/regularizers/__init__.py
neuralpy/layers/regularizers/alpha_dropout.py
neuralpy/layers/regularizers/dropout.py
neuralpy/layers/regularizers/dropout2d.py
neuralpy/layers/regularizers/dropout3d.py
neuralpy/layers/sparse/__init__.py
neuralpy/layers/sparse/embedding.py
neuralpy/loss_functions/__init__.py
neuralpy/loss_functions/bce_loss.py
neuralpy/loss_functions/cross_entropy.py
neuralpy/loss_functions/mse.py
neuralpy/models/__init__.py
neuralpy/models/model.py
neuralpy_torch-0.2.1.dist-info/LICENSE
neuralpy_torch-0.2.1.dist-info/METADATA
neuralpy_torch-0.2.1.dist-info/WHEEL
neuralpy_torch-0.2.1.dist-info/top_level.txt
neuralpy_torch-0.2.1.dist-info/RECORD
